pyxis/__init__.py
pyxis/time.py
pyxis/astro/__init__.py
pyxis/astro/coordinates.py
pyxis/astro/bodies/__init__.py
pyxis/astro/bodies/artificial.py
pyxis/astro/bodies/celestial.py
pyxis/astro/bodies/terrestrial.py
pyxis/astro/propagators/__init__.py
pyxis/astro/propagators/inertial.py
pyxis/astro/propagators/relative.py
pyxis/estimation/__init__.py
pyxis/estimation/filtering.py
pyxis/estimation/obs.py
pyxis/hardware/__init__.py
pyxis/hardware/constraints.py
pyxis/hardware/payloads.py
pyxis/math/__init__.py
pyxis/math/constants.py
pyxis/math/functions.py
pyxis/math/linalg.py
pyxis_toolkit-1.1.0.dist-info/LICENSE
pyxis_toolkit-1.1.0.dist-info/METADATA
pyxis_toolkit-1.1.0.dist-info/WHEEL
pyxis_toolkit-1.1.0.dist-info/top_level.txt
pyxis_toolkit-1.1.0.dist-info/RECORD
