Metadata-Version: 2.1
Name: pyxis-toolkit
Version: 1.1.0
Summary: astrodynamics analysis and simulation package
Author-email: Brandon Sexton <brandon.sexton@roguesolutions.us>
License: GNU GENERAL PUBLIC LICENSE
Project-URL: Homepage, https://www.pyxis-docs.com/
Requires-Python: >=3.8
License-File: LICENSE
